Workbook

Sheet Summary
A1: Infosys Limited
A2: Comparable Company Analysis - Summary
A3: Rs crore unless stated | Blue = reported data / input, Black = formula, Green = link from another sheet
A5: PEER SET
A6: TCS, HCLTech, Wipro, Tech Mahindra (Indian IT services large-caps). Prices at 28-Mar-2025; FY2025 results (year to 31-Mar-2025).
A8: TRADING MULTIPLES
A9: Company | B9: Market cap (Rs cr) | C9: EV (Rs cr) | D9: EV / EBITDA | E9: P / E | F9: EBITDA margin | G9: ROE
A10: TCS | B10: =Comps!D6 | C10: =Comps!I6 | D10: =Comps!O6 | E10: =Comps!P6 | F10: ='Operating Metrics'!D6 | G10: ='Operating Metrics'!G6
A11: HCLTech | B11: =Comps!D7 | C11: =Comps!I7 | D11: =Comps!O7 | E11: =Comps!P7 | F11: ='Operating Metrics'!D7 | G11: ='Operating Metrics'!G7
A12: Wipro | B12: =Comps!D8 | C12: =Comps!I8 | D12: =Comps!O8 | E12: =Comps!P8 | F12: ='Operating Metrics'!D8 | G12: ='Operating Metrics'!G8
A13: Tech Mahindra | B13: =Comps!D9 | C13: =Comps!I9 | D13: =Comps!O9 | E13: =Comps!P9 | F13: ='Operating Metrics'!D9 | G13: ='Operating Metrics'!G9
A14: Peer median | D14: =Comps!O12 | E14: =Comps!P12 | F14: ='Operating Metrics'!D12 | G14: ='Operating Metrics'!G12
A15: Peer mean | D15: =Comps!O11 | E15: =Comps!P11 | F15: ='Operating Metrics'!D11 | G15: ='Operating Metrics'!G11
A16: Infosys | B16: =Comps!D16 | C16: =Comps!I16 | D16: =Comps!O16 | E16: =Comps!P16 | F16: ='Operating Metrics'!D16 | G16: ='Operating Metrics'!G16
A19: WHAT THE PEER MULTIPLES SAY ABOUT INFOSYS
A20: Infosys EV / EBITDA vs peer median | B20: ='Comps'!O17
A21: Infosys P / E vs peer median | B21: ='Comps'!P17
A22: Implied value per share at peer-median EV / EBITDA (Rs) | B22: ='Implied Valuation'!C22
A23: Implied value per share at peer-median P / E (Rs) | B23: ='Implied Valuation'!C25
A24: Average of the two peer-median values (Rs) | B24: ='Implied Valuation'!C37
A25: Market price at 28-Mar-2025 (Rs) | B25: ='Implied Valuation'!C36
A26: DCF value per share, base case (Rs) | B26: ='Implied Valuation'!B15
A27: Peer-median value vs market price | B27: ='Implied Valuation'!C38
A29: Conclusion
A30: Infosys trades at a small discount to the peer median on both EV/EBITDA and P/E. Applying peer-median multiples gives a value above the market price, while the DCF base case gives a lower value, because the DCF assumes only moderate growth and a 11.7% discount rate. The comps range therefore supports the current market price, and the DCF shows how much growth or lower required return the price depends on.

Sheet Comps
A1: Infosys Limited
A2: Comparable Company Analysis - trading multiples at 28-Mar-2025 (FY2025 results)
A3: Rs crore unless stated | Blue = reported data / input, Black = formula, Green = link from another sheet
A5: Company | B5: Share price (Rs) | C5: Shares (crore) | D5: Market cap | E5: Debt | F5: Lease liabilities | G5: Minority interest | H5: Cash & investments | I5: Enterprise value (EV) | J5: Revenue FY25 | K5: EBITDA FY25 | L5: Profit after tax (owners) | M5: EPS (Rs) | N5: EV / Sales | O5: EV / EBITDA | P5: P / E
A6: TCS | B6: ='Source Data'!C8 | C6: ='Source Data'!C9/'Source Data'!C7/'Source Data'!C10 | D6: =B6*C6 | E6: ='Source Data'!C25/'Source Data'!C7 | F6: ='Source Data'!C26/'Source Data'!C7 | G6: ='Source Data'!C27/'Source Data'!C7 | H6: =('Source Data'!C21+'Source Data'!C22+'Source Data'!C23+'Source Data'!C24)/'Source Data'!C7 | I6: =D6+E6+F6+G6-H6 | J6: ='Source Data'!C11/'Source Data'!C7 | K6: =('Source Data'!C11-'Source Data'!C13)/'Source Data'!C7 | L6: ='Source Data'!C19/'Source Data'!C7 | M6: ='Source Data'!C20 | N6: =I6/J6 | O6: =I6/K6 | P6: =B6/M6
A7: HCLTech | B7: ='Source Data'!D8 | C7: ='Source Data'!D9/'Source Data'!D7/'Source Data'!D10 | D7: =B7*C7 | E7: ='Source Data'!D25/'Source Data'!D7 | F7: ='Source Data'!D26/'Source Data'!D7 | G7: ='Source Data'!D27/'Source Data'!D7 | H7: =('Source Data'!D21+'Source Data'!D22+'Source Data'!D23+'Source Data'!D24)/'Source Data'!D7 | I7: =D7+E7+F7+G7-H7 | J7: ='Source Data'!D11/'Source Data'!D7 | K7: =('Source Data'!D11-'Source Data'!D13)/'Source Data'!D7 | L7: ='Source Data'!D19/'Source Data'!D7 | M7: ='Source Data'!D20 | N7: =I7/J7 | O7: =I7/K7 | P7: =B7/M7
A8: Wipro | B8: ='Source Data'!E8 | C8: ='Source Data'!E9/'Source Data'!E7/'Source Data'!E10 | D8: =B8*C8 | E8: ='Source Data'!E25/'Source Data'!E7 | F8: ='Source Data'!E26/'Source Data'!E7 | G8: ='Source Data'!E27/'Source Data'!E7 | H8: =('Source Data'!E21+'Source Data'!E22+'Source Data'!E23+'Source Data'!E24)/'Source Data'!E7 | I8: =D8+E8+F8+G8-H8 | J8: ='Source Data'!E11/'Source Data'!E7 | K8: =('Source Data'!E11-'Source Data'!E13)/'Source Data'!E7 | L8: ='Source Data'!E19/'Source Data'!E7 | M8: ='Source Data'!E20 | N8: =I8/J8 | O8: =I8/K8 | P8: =B8/M8
A9: Tech Mahindra | B9: ='Source Data'!F8 | C9: ='Source Data'!F9/'Source Data'!F7/'Source Data'!F10 | D9: =B9*C9 | E9: ='Source Data'!F25/'Source Data'!F7 | F9: ='Source Data'!F26/'Source Data'!F7 | G9: ='Source Data'!F27/'Source Data'!F7 | H9: =('Source Data'!F21+'Source Data'!F22+'Source Data'!F23+'Source Data'!F24)/'Source Data'!F7 | I9: =D9+E9+F9+G9-H9 | J9: ='Source Data'!F11/'Source Data'!F7 | K9: =('Source Data'!F11-'Source Data'!F13)/'Source Data'!F7 | L9: ='Source Data'!F19/'Source Data'!F7 | M9: ='Source Data'!F20 | N9: =I9/J9 | O9: =I9/K9 | P9: =B9/M9
A11: Peer Mean | N11: =AVERAGE(N6:N9) | O11: =AVERAGE(O6:O9) | P11: =AVERAGE(P6:P9)
A12: Peer Median | N12: =MEDIAN(N6:N9) | O12: =MEDIAN(O6:O9) | P12: =MEDIAN(P6:P9)
A13: Peer High | N13: =MAX(N6:N9) | O13: =MAX(O6:O9) | P13: =MAX(P6:P9)
A14: Peer Low | N14: =MIN(N6:N9) | O14: =MIN(O6:O9) | P14: =MIN(P6:P9)
A16: Infosys Ltd. (subject) | B16: ='Source Data'!B8 | C16: ='Source Data'!B9/'Source Data'!B7/'Source Data'!B10 | D16: =B16*C16 | E16: ='Source Data'!B25/'Source Data'!B7 | F16: ='Source Data'!B26/'Source Data'!B7 | G16: ='Source Data'!B27/'Source Data'!B7 | H16: =('Source Data'!B21+'Source Data'!B22+'Source Data'!B23+'Source Data'!B24)/'Source Data'!B7 | I16: =D16+E16+F16+G16-H16 | J16: ='Source Data'!B11/'Source Data'!B7 | K16: =('Source Data'!B11-'Source Data'!B13)/'Source Data'!B7 | L16: ='Source Data'!B19/'Source Data'!B7 | M16: ='Source Data'!B20 | N16: =I16/J16 | O16: =I16/K16 | P16: =B16/M16
A17: Infosys premium / (discount) to peer median | N17: =N16/N12-1 | O17: =O16/O12-1 | P17: =P16/P12-1
A19: Enterprise value = market cap + borrowings + lease liabilities + minority interest - cash and investments (all investments, bank balances and deposits).
A20: EBITDA = revenue less operating costs before depreciation, finance cost, other income and exceptional items (post Ind AS 116, so leases are included in EV for consistency).
A21: Multiples use trailing FY2025 results (year ended 31-Mar-2025). No consensus estimates are used. Peer statistics exclude Infosys.

Sheet Operating Metrics
A1: Infosys Limited
A2: Operating and financial metrics - why the multiples differ
A3: Rs crore unless stated | Blue = reported data / input, Black = formula, Green = link from another sheet
A5: Company | B5: Revenue growth FY25 | C5: Profit growth FY25 | D5: EBITDA margin | E5: EBIT margin | F5: Net profit margin | G5: Return on equity | H5: Net cash % of market cap | I5: Free cash flow / net profit | J5: Capex % of revenue
A6: TCS | B6: ='Source Data'!C11/'Source Data'!C12-1 | C6: ='Source Data'!C17/'Source Data'!C18-1 | D6: =('Source Data'!C11-'Source Data'!C13)/'Source Data'!C11 | E6: =('Source Data'!C11-'Source Data'!C13-'Source Data'!C14)/'Source Data'!C11 | F6: ='Source Data'!C17/'Source Data'!C11 | G6: ='Source Data'!C19/'Source Data'!C28 | H6: =(Comps!H6-Comps!E6-Comps!F6)/Comps!D6 | I6: =('Source Data'!C29-'Source Data'!C30)/'Source Data'!C17 | J6: ='Source Data'!C30/'Source Data'!C11
A7: HCLTech | B7: ='Source Data'!D11/'Source Data'!D12-1 | C7: ='Source Data'!D17/'Source Data'!D18-1 | D7: =('Source Data'!D11-'Source Data'!D13)/'Source Data'!D11 | E7: =('Source Data'!D11-'Source Data'!D13-'Source Data'!D14)/'Source Data'!D11 | F7: ='Source Data'!D17/'Source Data'!D11 | G7: ='Source Data'!D19/'Source Data'!D28 | H7: =(Comps!H7-Comps!E7-Comps!F7)/Comps!D7 | I7: =('Source Data'!D29-'Source Data'!D30)/'Source Data'!D17 | J7: ='Source Data'!D30/'Source Data'!D11
A8: Wipro | B8: ='Source Data'!E11/'Source Data'!E12-1 | C8: ='Source Data'!E17/'Source Data'!E18-1 | D8: =('Source Data'!E11-'Source Data'!E13)/'Source Data'!E11 | E8: =('Source Data'!E11-'Source Data'!E13-'Source Data'!E14)/'Source Data'!E11 | F8: ='Source Data'!E17/'Source Data'!E11 | G8: ='Source Data'!E19/'Source Data'!E28 | H8: =(Comps!H8-Comps!E8-Comps!F8)/Comps!D8 | I8: =('Source Data'!E29-'Source Data'!E30)/'Source Data'!E17 | J8: ='Source Data'!E30/'Source Data'!E11
A9: Tech Mahindra | B9: ='Source Data'!F11/'Source Data'!F12-1 | C9: ='Source Data'!F17/'Source Data'!F18-1 | D9: =('Source Data'!F11-'Source Data'!F13)/'Source Data'!F11 | E9: =('Source Data'!F11-'Source Data'!F13-'Source Data'!F14)/'Source Data'!F11 | F9: ='Source Data'!F17/'Source Data'!F11 | G9: ='Source Data'!F19/'Source Data'!F28 | H9: =(Comps!H9-Comps!E9-Comps!F9)/Comps!D9 | I9: =('Source Data'!F29-'Source Data'!F30)/'Source Data'!F17 | J9: ='Source Data'!F30/'Source Data'!F11
A11: Peer Mean | B11: =AVERAGE(B6:B9) | C11: =AVERAGE(C6:C9) | D11: =AVERAGE(D6:D9) | E11: =AVERAGE(E6:E9) | F11: =AVERAGE(F6:F9) | G11: =AVERAGE(G6:G9) | H11: =AVERAGE(H6:H9) | I11: =AVERAGE(I6:I9) | J11: =AVERAGE(J6:J9)
A12: Peer Median | B12: =MEDIAN(B6:B9) | C12: =MEDIAN(C6:C9) | D12: =MEDIAN(D6:D9) | E12: =MEDIAN(E6:E9) | F12: =MEDIAN(F6:F9) | G12: =MEDIAN(G6:G9) | H12: =MEDIAN(H6:H9) | I12: =MEDIAN(I6:I9) | J12: =MEDIAN(J6:J9)
A13: Peer High | B13: =MAX(B6:B9) | C13: =MAX(C6:C9) | D13: =MAX(D6:D9) | E13: =MAX(E6:E9) | F13: =MAX(F6:F9) | G13: =MAX(G6:G9) | H13: =MAX(H6:H9) | I13: =MAX(I6:I9) | J13: =MAX(J6:J9)
A14: Peer Low | B14: =MIN(B6:B9) | C14: =MIN(C6:C9) | D14: =MIN(D6:D9) | E14: =MIN(E6:E9) | F14: =MIN(F6:F9) | G14: =MIN(G6:G9) | H14: =MIN(H6:H9) | I14: =MIN(I6:I9) | J14: =MIN(J6:J9)
A16: Infosys Ltd. (subject) | B16: ='Source Data'!B11/'Source Data'!B12-1 | C16: ='Source Data'!B17/'Source Data'!B18-1 | D16: =('Source Data'!B11-'Source Data'!B13)/'Source Data'!B11 | E16: =('Source Data'!B11-'Source Data'!B13-'Source Data'!B14)/'Source Data'!B11 | F16: ='Source Data'!B17/'Source Data'!B11 | G16: ='Source Data'!B19/'Source Data'!B28 | H16: =(Comps!H16-Comps!E16-Comps!F16)/Comps!D16 | I16: =('Source Data'!B29-'Source Data'!B30)/'Source Data'!B17 | J16: ='Source Data'!B30/'Source Data'!B11
A18: Reading the table
A19: Higher growth, higher margins and higher returns normally justify a higher multiple. Tech Mahindra's P/E is high because its profit is still recovering from a weak FY24 (EBITDA margin rose from about 9.5% to 13.2%).
A20: Net cash % of market cap shows balance-sheet strength: Infosys and TCS have no borrowings; Wipro holds a large net cash pile.
A21: Free cash flow / net profit shows how much of accounting profit turns into cash (operating cash flow less capex, divided by profit for the year).

Sheet Implied Valuation
A1: Infosys Limited
A2: What peer multiples imply for the Infosys share price
A3: Rs crore unless stated | Blue = reported data / input, Black = formula, Green = link from another sheet
A5: Infosys inputs (FY2025)
A6: Revenue | B6: =Comps!J16
A7: EBITDA | B7: =Comps!K16
A8: EPS (Rs) | B8: =Comps!M16
A9: Cash and investments | B9: =Comps!H16
A10: Borrowings | B10: =Comps!E16
A11: Lease liabilities | B11: =Comps!F16
A12: Minority interest | B12: =Comps!G16
A13: Diluted shares (crore) | B13: 415.205 | C13: Diluted weighted average shares, FY25 (as used in the DCF model)
A14: Market price, 28-Mar-2025 (Rs) | B14: =Comps!B16
A15: DCF value per share (Rs) | B15: 1128 | C15: From the Infosys DCF model (base case)
A17: Implied value per share from peer multiples (Rs)
A18: Method | B18: Peer low | C18: Peer median | D18: Peer mean | E18: Peer high
A19: Multiple: EV / EBITDA (x) | B19: =Comps!O14 | C19: =Comps!O12 | D19: =Comps!O11 | E19: =Comps!O13
A20: Implied enterprise value | B20: =B19*$B$7 | C20: =C19*$B$7 | D20: =D19*$B$7 | E20: =E19*$B$7
A21: Implied equity value | B21: =B20+$B$9-$B$10-$B$11-$B$12 | C21: =C20+$B$9-$B$10-$B$11-$B$12 | D21: =D20+$B$9-$B$10-$B$11-$B$12 | E21: =E20+$B$9-$B$10-$B$11-$B$12
A22: Implied value per share (Rs) | B22: =B21/$B$13 | C22: =C21/$B$13 | D22: =D21/$B$13 | E22: =E21/$B$13
A24: Multiple: P / E (x) | B24: =Comps!P14 | C24: =Comps!P12 | D24: =Comps!P11 | E24: =Comps!P13
A25: Implied value per share (Rs) | B25: =B24*$B$8 | C25: =C24*$B$8 | D25: =D24*$B$8 | E25: =E24*$B$8
A27: Multiple: EV / Sales (x) | B27: =Comps!N14 | C27: =Comps!N12 | D27: =Comps!N11 | E27: =Comps!N13
A28: Implied value per share (Rs) | B28: =((B27*$B$6)+$B$9-$B$10-$B$11-$B$12)/$B$13 | C28: =((C27*$B$6)+$B$9-$B$10-$B$11-$B$12)/$B$13 | D28: =((D27*$B$6)+$B$9-$B$10-$B$11-$B$12)/$B$13 | E28: =((E27*$B$6)+$B$9-$B$10-$B$11-$B$12)/$B$13
A29: EV / Sales is shown for completeness only; it ignores margin differences, so it is not used in the summary chart.
A31: Valuation summary (football field), Rs per share
A32: Method | B32: Low | C32: Median / base | D32: High | E32: Range (High - Low)
A33: Peer EV / EBITDA (low - high) | B33: =B22 | C33: =C22 | D33: =E22 | E33: =D33-B33
A34: Peer P / E (low - high) | B34: =B25 | C34: =C25 | D34: =E25 | E34: =D34-B34
A35: DCF, sensitivity range (WACC +/-1%, growth +/-1%) | B35: 903 | C35: =B15 | D35: 1568 | E35: =D35-B35
A36: Market price, 28-Mar-2025 (Rs) | C36: =B14
A37: Average of peer-median values (EV/EBITDA and P/E), Rs | C37: =AVERAGE(C22,C25)
A38: Peer-median value vs market price | C38: =C37/C36-1

Sheet Source Data
A1: Source Data
A2: Reported figures from consolidated financial statements, year ended 31 March 2025
A3: Rs crore unless stated | Blue = reported data / input, Black = formula, Green = link from another sheet
A5: Item | B5: Infosys | C5: TCS | D5: HCLTech | E5: Wipro | F5: Tech Mahindra | G5: Source / note
A6: Unit of reported figures | B6: Rs crore | C6: Rs crore | D6: Rs crore | E6: Rs million | F6: Rs million | G6: Wipro and Tech Mahindra report in Rs million (1 crore = 10 million)
A7: Divisor to convert to Rs crore | B7: 1 | C7: 1 | D7: 1 | E7: 10 | F7: 10 | G7: Used by the Comps sheet to convert every figure to Rs crore
A8: Share price, NSE close 28-Mar-2025 (Rs) | B8: 1570.65 | C8: 3606.15 | D8: 1592.5 | E8: 262.25 | F8: 1418.25 | G8: Yahoo Finance daily NSE close, 28-Mar-2025 (last trading day of FY25). Cross-checks: Wipro report NSE price Rs262.3; TCS report P/E 26.9x x EPS Rs134.19 = Rs3,610
A9: Share capital | B9: 2073 | C9: 362 | D9: 543 | E9: 20944 | F9: 4424 | G9: Balance sheet, equity share capital (reported units)
A10: Face value per share (Rs) | B10: 5 | C10: 1 | D10: 2 | E10: 2 | F10: 5 | G10: Annual reports
A11: Revenue from operations, FY25 | B11: 162990 | C11: 255324 | D11: 117055 | E11: 890884 | F11: 529883 | G11: Consolidated statement of profit and loss
A12: Revenue from operations, FY24 | B12: 153670 | C12: 240893 | D12: 109913 | E12: 897603 | F12: 519955 | G12: Prior-year comparative (HCLTech FY24 from five-year trend table)
A13: Operating costs excl. D&A, finance cost, other income and exceptionals, FY25 | B13: 123754 | C13: 187917 | D13: 91551 | E13: 710672 | F13: 459972 | G13: Infosys: total opex excl. D&A. TCS: employee 145,788 + equipment/software 11,648 + other 30,481. HCLTech: stock-in-trade 1,976 + inventory change 52 + employee 66,755 + outsourcing 15,162 + other 7,606. Wipro: all expense lines except finance cost and D&A (710,672). Tech Mahindra: employee 296,238 + subcontracting 58,377 + other 105,357
A14: Depreciation and amortisation, FY25 | B14: 4812 | C14: 5242 | D14: 4084 | E14: 29579 | F14: 18529 | G14: Wipro figure includes impairment
A15: Other income, FY25 | B15: 3600 | C15: 3962 | D15: 2485 | E15: 38840 | F15: 8554 | G15: Excluded from EBITDA for all companies
A16: Finance cost, FY25 | B16: 416 | C16: 796 | D16: 644 | E16: 14770 | F16: 3217 | G16: Includes lease interest
A17: Profit for the year, FY25 | B17: 26750 | C17: 48797 | D17: 17399 | E17: 132180 | F17: 42530 | G17: Consolidated, before minority interests
A18: Profit for the year, FY24 | B18: 26248 | C18: 46099 | D18: 15710 | E18: 111121 | F18: 23968 | G18: HCLTech FY24 from five-year trend table. Tech Mahindra FY24 depressed by Rs458 crore goodwill impairment
... A30: Capital expenditure, FY25 | B30: 2237 | C30: 3861 | D30: 1108 | E30: 14737 | F30: 5935 | G30: PPE and intangibles. Wipro: PPE only (intangible purchases not separately material)
A32: Data notes
A33: HCLTech: the uploaded file is the annual report for the year ended 31 March 2026; all figures here are its 31-Mar-2025 / FY2025 comparatives (as presented in that report).
A34: TCS, Wipro, Tech Mahindra: annual reports for the year ended 31 March 2025. Infosys: annual report 2024-25.
A35: All companies prepare consolidated Ind AS statements with lease expense recognised as depreciation and interest, so EBITDA is comparable across the five.

Sheet Notes
A1: Infosys Limited - Comparable Company Analysis: Method and Notes
A3: Purpose
A4: Value Infosys relative to listed Indian IT services peers using trading multiples, as a cross-check to the DCF valuation (base date 31 March 2025).
A6: Peer set
A7: TCS, HCLTech, Wipro and Tech Mahindra: large Indian IT services companies with consolidated Ind AS reporting and a March year-end. LTIMindtree was excluded by choice.
A9: Method
A10: 1. Market capitalisation = NSE closing price on 28 March 2025 (last trading day of FY25) x shares (share capital / face value).
A11: 2. Enterprise value = market cap + borrowings + lease liabilities + minority interest - cash, bank balances and investments.
A12: 3. EBITDA = revenue - operating costs (excluding depreciation, finance cost, other income and exceptional items). Other income is excluded because it is earned on the cash that is deducted in EV.
A13: 4. Multiples: EV/Sales, EV/EBITDA and P/E (price / basic EPS), all on FY2025 results. Peer mean, median, high and low exclude Infosys.
A14: 5. Implied Infosys value: peer multiple x Infosys EBITDA (then bridge to equity value and divide by diluted shares), or peer P/E x Infosys EPS.
A16: Data sources
... A21: Trailing (FY25) multiples only; no consensus forward estimates. Share counts are share capital / face value and ignore treasury shares. Tech Mahindra FY25 earnings were still recovering, which inflates its P/E. Infosys price here is the NSE close (Rs1,570.65) while the DCF used a price derived from reported market capitalisation (Rs1,573.4); the difference is 0.2%. A four-company peer set is small, so the median is sensitive to any one company.
